agentsim/AbstractAgent.py
agentsim/Simulator.py
agentsim/__init__.py
agentsim/types.py
agentsim/utils.py
agentsim/agents/SimpleChatbot.py
agentsim/agents/__init__.py
agentsim/evaluators/TODO
agentsim/evaluators/__init__.py
agentsim/evaluators/message_limit.py
agentsim/evaluators/toxicity_score_llm.py
agentsim/evaluators/targets/BaseTarget.py
agentsim/evaluators/targets/ContainsTarget.py
agentsim/evaluators/targets/NumericRangeTarget.py
agentsim/evaluators/targets/ProximityTarget.py
agentsim/evaluators/targets/StringTarget.py
agentsim/evaluators/targets/__init__.py
agentsim/evaluators/utils/__init__.py
agentsim/evaluators/utils/score.py
agentsim/tests/targets/test_targets.py
agentsim-0.0.2.dist-info/LICENSE
agentsim-0.0.2.dist-info/METADATA
agentsim-0.0.2.dist-info/WHEEL
agentsim-0.0.2.dist-info/top_level.txt
agentsim-0.0.2.dist-info/RECORD
